drumsT/DrumsT.py
drumsT/__init__.py
drumsT/drumsT_DATA/__init__.py
drumsT/drumsT_DATA/data_info.py
drumsT/drumsT_DIALOGS/__init__.py
drumsT/drumsT_DIALOGS/add_newyear.py
drumsT/drumsT_DIALOGS/add_school.py
drumsT/drumsT_DIALOGS/add_student.py
drumsT/drumsT_DIALOGS/first_time_start.py
drumsT/drumsT_DIALOGS/infoprg.py
drumsT/drumsT_FRAMES/__init__.py
drumsT/drumsT_FRAMES/lessons.py
drumsT/drumsT_FRAMES/mainwindow.py
drumsT/drumsT_PANELS/__init__.py
drumsT/drumsT_PANELS/add_lesson.py
drumsT/drumsT_PANELS/lessons_prospective.py
drumsT/drumsT_SYS/SQLite_lib.py
drumsT/drumsT_SYS/__init__.py
drumsT/drumsT_SYS/app_const.py
drumsT/drumsT_SYS/boot.py
drumsT/drumsT_SYS/os_filesystem.py
drumst-1.0.0.data/data/share/applications/drumst.desktop
drumst-1.0.0.data/data/share/drumst/AUTHORS
drumst-1.0.0.data/data/share/drumst/BUGS
drumst-1.0.0.data/data/share/drumst/CHANGELOG
drumst-1.0.0.data/data/share/drumst/COPYING
drumst-1.0.0.data/data/share/drumst/INSTALL
drumst-1.0.0.data/data/share/drumst/README.md
drumst-1.0.0.data/data/share/drumst/TODO
drumst-1.0.0.data/data/share/drumst/config/drumsT.conf
drumst-1.0.0.data/data/share/drumst/icons/addStudent.png
drumst-1.0.0.data/data/share/drumst/icons/changeStudent.png
drumst-1.0.0.data/data/share/drumst/icons/delStudent.png
drumst-1.0.0.data/data/share/drumst/icons/drumsT.png
drumst-1.0.0.data/data/share/drumst/icons/icon_help.png
drumst-1.0.0.data/data/share/drumst/icons/lesson.png
drumst-1.0.0.data/data/share/drumst/icons/openStudent.png
drumst-1.0.0.data/data/share/drumst/icons/opentab.png
drumst-1.0.0.data/data/share/locale/it_IT/LC_MESSAGES/drumst.mo
drumst-1.0.0.data/data/share/pixmaps/drumsT.png
drumst-1.0.0.data/scripts/drumst
drumst-1.0.0.dist-info/AUTHORS
drumst-1.0.0.dist-info/COPYING
drumst-1.0.0.dist-info/METADATA
drumst-1.0.0.dist-info/WHEEL
drumst-1.0.0.dist-info/entry_points.txt
drumst-1.0.0.dist-info/top_level.txt
drumst-1.0.0.dist-info/RECORD
